{
  "project_info": {
    "project_number": "440903361494",
    "project_id": "crypto-currency-48a63",
    "storage_bucket": "crypto-currency-48a63.appspot.com"
  },
  "client": [
    {
      "client_info": {
        "mobilesdk_app_id": "1:440903361494:android:59fd7b81481a7879277a77",
        "android_client_info": {
          "package_name": "com.example.bitcoin"
        }
      },
      "oauth_client": [
        {
          "client_id": "440903361494-5pup9sksmsdbbj5pblfsvajav78slldn.apps.googleusercontent.com",
          "client_type": 3
        }
      ],
      "api_key": [
        {
          "current_key": "AIzaSyAwxNwhypMADU8INFuEiYcJEQh8V1kdmhs"
        }
      ],
      "services": {
        "appinvite_service": {
          "other_platform_oauth_client": [
            {
              "client_id": "440903361494-5pup9sksmsdbbj5pblfsvajav78slldn.apps.googleusercontent.com",
              "client_type": 3
            }
          ]
        }
      }
    }
  ],
  "configuration_version": "1"
}